{
  "update_time": "2026-02-26",
  "total_stocks": 4683,
  "data_source": "Tushare Pro",
  "strategy": "多维量化选股",
  "top20": [
    {
      "code": "600589.SH",
      "name": "大位科技",
      "close": 12.55,
      "change": 5.82,
      "score": 81.7,
      "ema_status": "多头排列",
      "stoch_status": "正常",
      "macd_status": "金叉",
      "vol_status": "放量",
      "momentum": 33.8,
      "rank": 1,
      "stochastic_k": 58.7,
      "stochastic_d": 51.8,
      "macd_val": 0.278,
      "volume_ratio": 1.7
    },
    {
      "code": "002506.SZ",
      "name": "协鑫集成",
      "close": 5.03,
      "change": 3.07,
      "score": 80.4,
      "ema_status": "多头排列",
      "stoch_status": "正常",
      "macd_status": "金叉",
      "vol_status": "放量",
      "momentum": 76.49,
      "rank": 2,
      "stochastic_k": 71.5,
      "stochastic_d": 65.6,
      "macd_val": 0.108,
      "volume_ratio": 1.21
    },
    {
      "code": "002455.SZ",
      "name": "百川股份",
      "close": 14.1,
      "change": -1.54,
      "score": 80.1,
      "ema_status": "多头排列",
      "stoch_status": "正常",
      "macd_status": "金叉",
      "vol_status": "放量",
      "momentum": 94.21,
      "rank": 3,
      "stochastic_k": 77.2,
      "stochastic_d": 83.4,
      "macd_val": 0.639,
      "volume_ratio": 1.45
    },
    {
      "code": "300570.SZ",
      "name": "太辰光",
      "close": 143.7,
      "change": 3.15,
      "score": 80.0,
      "ema_status": "多头排列",
      "stoch_status": "正常",
      "macd_status": "金叉",
      "vol_status": "平量",
      "momentum": 34.3,
      "rank": 4,
      "stochastic_k": 71.0,
      "stochastic_d": 71.6,
      "macd_val": 4.09,
      "volume_ratio": 1.04
    },
    {
      "code": "300265.SZ",
      "name": "通光线缆",
      "close": 18.3,
      "change": 8.67,
      "score": 79.9,
      "ema_status": "多头排列",
      "stoch_status": "超买",
      "macd_status": "金叉",
      "vol_status": "平量",
      "momentum": 31.28,
      "rank": 5,
      "stochastic_k": 84.2,
      "stochastic_d": 79.5,
      "macd_val": 0.28,
      "volume_ratio": 1.17
    },
    {
      "code": "603960.SH",
      "name": "克来机电",
      "close": 26.24,
      "change": 2.38,
      "score": 79.0,
      "ema_status": "多头排列",
      "stoch_status": "正常",
      "macd_status": "金叉",
      "vol_status": "放量",
      "momentum": 24.71,
      "rank": 6,
      "stochastic_k": 67.3,
      "stochastic_d": 66.9,
      "macd_val": 0.774,
      "volume_ratio": 1.74
    },
    {
      "code": "002519.SZ",
      "name": "银河电子",
      "close": 10.27,
      "change": -4.02,
      "score": 78.8,
      "ema_status": "多头排列",
      "stoch_status": "超买",
      "macd_status": "金叉",
      "vol_status": "平量",
      "momentum": 19.42,
      "rank": 7,
      "stochastic_k": 80.4,
      "stochastic_d": 84.9,
      "macd_val": 0.228,
      "volume_ratio": 1.11
    },
    {
      "code": "603138.SH",
      "name": "海量数据",
      "close": 22.26,
      "change": -0.31,
      "score": 78.6,
      "ema_status": "多头排列",
      "stoch_status": "正常",
      "macd_status": "金叉",
      "vol_status": "放量",
      "momentum": 36.48,
      "rank": 8,
      "stochastic_k": 75.1,
      "stochastic_d": 69.8,
      "macd_val": 0.791,
      "volume_ratio": 1.7
    },
    {
      "code": "002806.SZ",
      "name": "华锋股份",
      "close": 16.84,
      "change": 2.06,
      "score": 78.6,
      "ema_status": "多头排列",
      "stoch_status": "超买",
      "macd_status": "金叉",
      "vol_status": "平量",
      "momentum": 24.56,
      "rank": 9,
      "stochastic_k": 88.1,
      "stochastic_d": 81.8,
      "macd_val": 0.466,
      "volume_ratio": 1.08
    },
    {
      "code": "603150.SH",
      "name": "万朗磁塑",
      "close": 61.36,
      "change": 5.67,
      "score": 78.5,
      "ema_status": "多头排列",
      "stoch_status": "正常",
      "macd_status": "金叉",
      "vol_status": "平量",
      "momentum": 39.71,
      "rank": 10,
      "stochastic_k": 78.6,
      "stochastic_d": 74.3,
      "macd_val": 1.699,
      "volume_ratio": 1.16
    },
    {
      "code": "002207.SZ",
      "name": "准油股份",
      "close": 11.5,
      "change": -0.78,
      "score": 78.4,
      "ema_status": "多头排列",
      "stoch_status": "正常",
      "macd_status": "金叉",
      "vol_status": "平量",
      "momentum": 29.36,
      "rank": 11,
      "stochastic_k": 76.0,
      "stochastic_d": 72.9,
      "macd_val": 0.152,
      "volume_ratio": 0.81
    },
    {
      "code": "600345.SH",
      "name": "长江通信",
      "close": 43.51,
      "change": 1.45,
      "score": 78.3,
      "ema_status": "多头排列",
      "stoch_status": "超买",
      "macd_status": "金叉",
      "vol_status": "平量",
      "momentum": 33.71,
      "rank": 12,
      "stochastic_k": 82.4,
      "stochastic_d": 83.9,
      "macd_val": 0.873,
      "volume_ratio": 0.94
    },
    {
      "code": "000070.SZ",
      "name": "特发信息",
      "close": 18.12,
      "change": -0.11,
      "score": 77.9,
      "ema_status": "多头排列",
      "stoch_status": "正常",
      "macd_status": "金叉",
      "vol_status": "放量",
      "momentum": 55.4,
      "rank": 13,
      "stochastic_k": 79.2,
      "stochastic_d": 79.6,
      "macd_val": 0.977,
      "volume_ratio": 1.57
    },
    {
      "code": "002323.SZ",
      "name": "雅博股份",
      "close": 2.48,
      "change": 6.44,
      "score": 77.9,
      "ema_status": "多头排列",
      "stoch_status": "正常",
      "macd_status": "金叉",
      "vol_status": "放量",
      "momentum": 46.75,
      "rank": 14,
      "stochastic_k": 75.0,
      "stochastic_d": 63.0,
      "macd_val": 0.116,
      "volume_ratio": 2.21
    },
    {
      "code": "301526.SZ",
      "name": "国际复材",
      "close": 15.6,
      "change": -1.02,
      "score": 77.7,
      "ema_status": "多头排列",
      "stoch_status": "超买",
      "macd_status": "金叉",
      "vol_status": "放量",
      "momentum": 79.52,
      "rank": 15,
      "stochastic_k": 93.1,
      "stochastic_d": 96.1,
      "macd_val": 1.303,
      "volume_ratio": 1.28
    },
    {
      "code": "601890.SH",
      "name": "亚星锚链",
      "close": 13.33,
      "change": -0.52,
      "score": 77.6,
      "ema_status": "多头排列",
      "stoch_status": "超买",
      "macd_status": "金叉",
      "vol_status": "放量",
      "momentum": 19.98,
      "rank": 16,
      "stochastic_k": 84.4,
      "stochastic_d": 90.2,
      "macd_val": 0.547,
      "volume_ratio": 2.07
    },
    {
      "code": "600722.SH",
      "name": "金牛化工",
      "close": 9.65,
      "change": -2.92,
      "score": 77.5,
      "ema_status": "多头排列",
      "stoch_status": "正常",
      "macd_status": "金叉",
      "vol_status": "平量",
      "momentum": 39.45,
      "rank": 17,
      "stochastic_k": 74.4,
      "stochastic_d": 79.4,
      "macd_val": 0.148,
      "volume_ratio": 1.08
    },
    {
      "code": "601231.SH",
      "name": "环旭电子",
      "close": 43.31,
      "change": -3.63,
      "score": 77.5,
      "ema_status": "多头排列",
      "stoch_status": "正常",
      "macd_status": "金叉",
      "vol_status": "平量",
      "momentum": 36.15,
      "rank": 18,
      "stochastic_k": 67.8,
      "stochastic_d": 85.4,
      "macd_val": 1.511,
      "volume_ratio": 1.0
    },
    {
      "code": "603466.SH",
      "name": "风语筑",
      "close": 12.65,
      "change": -2.47,
      "score": 77.3,
      "ema_status": "多头排列",
      "stoch_status": "正常",
      "macd_status": "金叉",
      "vol_status": "放量",
      "momentum": 32.46,
      "rank": 19,
      "stochastic_k": 73.8,
      "stochastic_d": 84.6,
      "macd_val": 0.76,
      "volume_ratio": 2.39
    },
    {
      "code": "300157.SZ",
      "name": "新锦动力",
      "close": 6.93,
      "change": -1.0,
      "score": 77.3,
      "ema_status": "多头排列",
      "stoch_status": "超买",
      "macd_status": "金叉",
      "vol_status": "平量",
      "momentum": 34.82,
      "rank": 20,
      "stochastic_k": 84.7,
      "stochastic_d": 90.9,
      "macd_val": 0.179,
      "volume_ratio": 1.05
    }
  ]
}